Metadata-Version: 2.1
Name: hyperoptim
Version: 0.0.1
Summary: Hyperparameter Optimization using Genetic Algorithms.
Home-page: https://github.com/deepak7376/hyperoptim
Author: Deepak Yadav
Author-email: dky.united@gmail.com
License: MIT
Keywords: Hyperparameter optimization using Genetic Algorithms.
Platform: UNKNOWN
Classifier: Development Status :: 3 - Alpha
Classifier: Intended Audience :: Developers
Classifier: Topic :: Scientific/Engineering :: Mathematics
Classifier: License :: OSI Approved :: MIT License
Classifier: Programming Language :: Python :: 3.0
Requires-Python: >=3
License-File: LICENSE
